adafruit_displayio_sh1107.py
adafruit_circuitpython_displayio_sh1107-2.0.4.dist-info/licenses/LICENSE
adafruit_circuitpython_displayio_sh1107-2.0.4.dist-info/METADATA
adafruit_circuitpython_displayio_sh1107-2.0.4.dist-info/WHEEL
adafruit_circuitpython_displayio_sh1107-2.0.4.dist-info/top_level.txt
adafruit_circuitpython_displayio_sh1107-2.0.4.dist-info/RECORD
