Metadata-Version: 2.4
Name: adafruit-circuitpython-displayio-sh1107
Version: 2.0.4
Summary: Support for the SH1107 OLED display driver IC
Author-email: Adafruit Industries <circuitpython@adafruit.com>
License: MIT
Project-URL: Homepage, https://github.com/adafruit/Adafruit_CircuitPython_DisplayIO_SH1107
Keywords: adafruit,blinka,circuitpython,micropython,displayio_sh1107,display,oled
Classifier: Intended Audience :: Developers
Classifier: Topic :: Software Development :: Libraries
Classifier: Topic :: Software Development :: Embedded Systems
Classifier: Topic :: System :: Hardware
Classifier: License :: OSI Approved :: MIT License
Classifier: Programming Language :: Python :: 3
License-File: LICENSE
Requires-Dist: Adafruit-Blinka
Requires-Dist: Adafruit-Blinka-Displayio
Provides-Extra: optional
Dynamic: license-file
